Workbook

Sheet 前提条件
A1: 前提条件(黄色セルを差し替えると全シートが再計算されます)
A2: 項目 | B2: 値 | C2: 備考
A3: 客単価(円) | B3: 900 | C3: 【仮】ポップアップのテストマーケで確定
A4: 営業日数(日/月) | B4: 22 | C4: 【仮】週5営業想定
A5: 客数/日:保守シナリオ | B5: 25 | C5: 【仮】
A6: 客数/日:標準シナリオ | B6: 40 | C6: 【仮】
A7: 客数/日:強気シナリオ | B7: 60 | C7: 【仮】
A8: 原価率 | B8: 0.32 | C8: 【仮】カフェ・軽食業態の一般的水準
A9: 土地代(月) | B9: 30000 | C9: 【仮】自社・家族所有地なら0に変更
A10: 保恵さん給与(月) | B10: 200000 | C10: 【仮】専業化後
A11: 美慧さん謝礼(月) | B11: 30000 | C11: 【仮】週末ヘルプ想定
A12: 水道光熱費(月) | B12: 30000 | C12: 【仮】3坪・電化厨房
A13: 通信・レジ(月) | B13: 10000 | C13: 【仮】iPadレジ・回線
A14: 消耗品・雑費(月) | B14: 20000 | C14: 【仮】
... A19: 返済年数 | B19: 5 | C19: 【仮】据置期間なし

Sheet 初期投資
A1: 初期投資計画(【仮】上限イメージ500万円で設定)
A2: 項目 | B2: 金額 | C2: 備考
A3: コンテナ本体 | B3: 0 | C3: 無料入手済み
A4: コンテナ改装工事(断熱・内装・電気・給排水) | B4: 2500000 | C4: 【仮】保健所基準対応込み。光和工業の知見で圧縮余地あり
A5: パニーニクッカー 1連式 PC-10 | B5: 168000 | C5: ノート備品リストの実価格
A6: ハリオ コーヒーサイフォン テクニカ TCAR-5 | B6: 12000 | C6: ノート備品リストの実価格
A7: エスプレッソマシン・グラインダー | B7: 300000 | C7: 【仮】中古・リース検討で圧縮余地あり
A8: 冷蔵・冷凍庫 | B8: 250000 | C8: 【仮】
A9: シンク・作業台・給湯設備 | B9: 200000 | C9: 【仮】保健所基準(2槽シンク等)要確認
A10: 外構(ウッドデッキ・テラス・アニマルフレンドエリア) | B10: 600000 | C10: 【仮】DIY施工で圧縮余地あり
A11: 食器・カップ・ストロー等 初期備品 | B11: 150000 | C11: 【仮】ノート備品リストより
A12: iPadレジ・通信機器 | B12: 100000 | C12: 【仮】
A13: 看板・ロゴ・ショップカード等デザイン | B13: 200000 | C13: 【仮】
A14: 許認可・講習・保険 | B14: 50000 | C14: 食品衛生責任者講習9,900円ほか
... A16: 予備費 | B16: 370000 | C16: 【仮】総額の約7%
A17: 合計 | B17: =SUM(B3:B16)

Sheet 月次収支
A1: 月次収支シミュレーション(3シナリオ)
A2: 項目 | B2: 保守 | C2: 標準 | D2: 強気
A3: 客数/日 | B3: =前提条件!$B$5 | C3: =前提条件!$B$6 | D3: =前提条件!$B$7
A4: 売上高 | B4: =前提条件!$B$3*前提条件!$B$4*B3 | C4: =前提条件!$B$3*前提条件!$B$4*C3 | D4: =前提条件!$B$3*前提条件!$B$4*D3
A5: 売上原価 | B5: =B4*前提条件!$B$8 | C5: =C4*前提条件!$B$8 | D5: =D4*前提条件!$B$8
A6: 売上総利益(粗利) | B6: =B4-B5 | C6: =C4-C5 | D6: =D4-D5
A7: 土地代 | B7: =前提条件!$B$9 | C7: =前提条件!$B$9 | D7: =前提条件!$B$9
A8: 人件費(保恵さん給与) | B8: =前提条件!$B$10 | C8: =前提条件!$B$10 | D8: =前提条件!$B$10
A9: 人件費(美慧さん謝礼) | B9: =前提条件!$B$11 | C9: =前提条件!$B$11 | D9: =前提条件!$B$11
A10: 水道光熱費 | B10: =前提条件!$B$12 | C10: =前提条件!$B$12 | D10: =前提条件!$B$12
A11: 通信・レジ | B11: =前提条件!$B$13 | C11: =前提条件!$B$13 | D11: =前提条件!$B$13
A12: 消耗品・雑費 | B12: =前提条件!$B$14 | C12: =前提条件!$B$14 | D12: =前提条件!$B$14
A13: 販促費 | B13: =前提条件!$B$15 | C13: =前提条件!$B$15 | D13: =前提条件!$B$15
A14: 保険・その他 | B14: =前提条件!$B$16 | C14: =前提条件!$B$16 | D14: =前提条件!$B$16
A15: 固定費計 | B15: =SUM(B7:B14) | C15: =SUM(C7:C14) | D15: =SUM(D7:D14)
A16: 営業利益 | B16: =B6-B15 | C16: =C6-C15 | D16: =D6-D15
A17: 借入返済(元利均等・月額) | B17: =-PMT(前提条件!$B$18/12,前提条件!$B$19*12,前提条件!$B$17) | C17: =-PMT(前提条件!$B$18/12,前提条件!$B$19*12,前提条件!$B$17) | D17: =-PMT(前提条件!$B$18/12,前提条件!$B$19*12,前提条件!$B$17)
A18: 返済後キャッシュ | B18: =B16-B17 | C18: =C16-C17 | D18: =D16-D17
A19: 年間営業利益 | B19: =B16*12 | C19: =C16*12 | D19: =D16*12
A20: 年間返済後キャッシュ | B20: =B18*12 | C20: =C18*12 | D20: =D18*12

Sheet 損益分岐点
A1: 損益分岐点分析
A2: 項目 | B2: 値 | C2: 計算式
A3: 固定費(月) | B3: =月次収支!B15 | C3: 月次収支の固定費計
A4: 粗利率 | B4: =1-前提条件!$B$8 | C4: 1-原価率
A5: 借入返済(月) | B5: =月次収支!B17 | C5: 元利均等月額
A6: 損益分岐点 月商(営業ベース) | B6: =B3/B4 | C6: 固定費÷粗利率
A7: 損益分岐点 客数/日(営業ベース) | B7: =B6/前提条件!$B$3/前提条件!$B$4 | C7: 月商÷客単価÷営業日数
A8: 損益分岐点 月商(返済込み) | B8: =(B3+B5)/B4 | C8: (固定費+返済)÷粗利率
A9: 損益分岐点 客数/日(返済込み) | B9: =B8/前提条件!$B$3/前提条件!$B$4 | C9: 月商÷客単価÷営業日数
